{
  "answer_by": null, 
  "answers": [
    {
      "author": "Alexandra Iannolo", 
      "score": "0", 
      "text": "\n\nHello,\nA question similar to yours was asked once before on the Knowledge Network. You can see the link to that and its answer below.\nhttp://icma.org/en/icma/knowledge_network/questions/question/20383\nI also found examples of places that have begun to implement paperless policies. You can contact them directly for more information about their efforts to go paperless.\nWashtenaw County, MI won an award for their work on going green through paperless solutions.\nhttp://icma.org/en/Article/100680/Washtenaw_County_MI_Receives_Award_for_Going_Paperless\nI also found a case study about the Colorado Housing and Finance Authority which recently conducted an ROI to see how paperless technology would affect them.\nhttp://www.kofax.com/case-studies/colorado-housing-and-finance-authority-chfa-achieves-rapid-roi-through-capture-enabled-enterprise-content-management/\nI have included a link to Paperless Project, a website which has more general information about eliminating paper from your offices.\nhttp://www.thepaperlessproject.com/about.html\nI hope these help!\nAli Iannolo\nKnowledge Network Intern\naiannolo@ICMA.org\n\n\nHello,\n\nA question similar to yours was asked once before on the Knowledge Network. You can see the link to that and its answer below.\nhttp://icma.org/en/icma/knowledge_network/questions/question/20383\nI also found examples of places that have begun to implement paperless policies. You can contact them directly for more information about their efforts to go paperless.\nWashtenaw County, MI won an award for their work on going green through paperless solutions.\nhttp://icma.org/en/Article/100680/Washtenaw_County_MI_Receives_Award_for_Going_Paperless\nI also found a case study about the Colorado Housing and Finance Authority which recently conducted an ROI to see how paperless technology would affect them.\nhttp://www.kofax.com/case-studies/colorado-housing-and-finance-authority-chfa-achieves-rapid-roi-through-capture-enabled-enterprise-content-management/\nI have included a link to Paperless Project, a website which has more general information about eliminating paper from your offices.\nhttp://www.thepaperlessproject.com/about.html\n\nI hope these help!\nAli Iannolo\nKnowledge Network Intern\naiannolo@ICMA.org\n\n\nSave Changes\nCancel\n\n\n\n", 
      "when": "30-08-2011"
    }
  ], 
  "answers_count": 1, 
  "author": "Gregory Stopka", 
  "id": 21307, 
  "score": "0", 
  "tags": [
    "Finance and Budgeting"
  ], 
  "text": "\n\nAn Alliance member has been tracking their ROI from going paperless.  Have any other cities/counties tracked their short and long-term savings?\n\n", 
  "title": "Paperless ROI?", 
  "when": "26-08-2011"
}