{
  "answer_by": null, 
  "answers": [], 
  "answers_count": 0, 
  "author": "Brad Larson", 
  "id": 22303, 
  "score": "0", 
  "tags": [
    "Transportation", 
    "Economic Development"
  ], 
  "text": "\n\nWe are considering a condo regime to manage the commercial space that will be built with a new public parking ramp.  Are their other communities that have used this approach before?  Do you have copies of the Declaration document that established the regime?\n\n", 
  "title": "Condo regime for public parking ramp", 
  "when": "26-11-2012"
}