{
  "answer_by": null, 
  "answers": [
    {
      "author": "Kenneth Decker", 
      "score": "0", 
      "text": "\n\nWe provide cell phones rather than pay a stipend (though we strongly considered the stipend model).  Every year, we audit who has a County-issued cell phone and why.  We monitor use and we've begun the transition to providing a tablet to replace a laptop and cell phone.\n\n\nWe provide cell phones rather than pay a stipend (though we strongly considered the stipend model).  Every year, we audit who has a County-issued cell phone and why.  We monitor use and we've begun the transition to providing a tablet to replace a laptop and cell phone.\n\n\nSave Changes\nCancel\n\n\n\n", 
      "when": "28-05-2014"
    }, 
    {
      "author": "[Unknown]", 
      "score": "0", 
      "text": "\n\nHi Joseph, \nIn this previously asked question local government officials talk about the pros and cons of having cell phone stipends vs. providing cell phones. There are also supporting documents and examples of both types of policy. \nhttp://icma.org/en/icma/knowledge_network/kn/Question/20483\nBest, \nRobin Saywitz \nICMA Knowledge Network Intern \nrsaywitz@icma.org\n\n\nHi Joseph, \n\nIn this previously asked question local government officials talk about the pros and cons of having cell phone stipends vs. providing cell phones. There are also supporting documents and examples of both types of policy. \nhttp://icma.org/en/icma/knowledge_network/kn/Question/20483\n\nBest, \nRobin Saywitz \nICMA Knowledge Network Intern \nrsaywitz@icma.org\n\n\nSave Changes\nCancel\n\n\n\n", 
      "when": "29-05-2014"
    }
  ], 
  "answers_count": 2, 
  "author": "Joseph Anzivino", 
  "id": 23151, 
  "score": "0", 
  "tags": [
    "Process Improvement"
  ], 
  "text": "\n\nHas anyone considered eliminating the cell phone stipend?\n\n", 
  "title": "Elimination of cell phone stipend", 
  "when": "28-05-2014"
}