{
  "answer_by": null, 
  "answers": [
    {
      "author": "REGGIE TAYLOR", 
      "score": "0", 
      "text": "\n\nI have a sample you can review just email me at rtaylor@mariettaga.gov.\n\n\nI have a sample you can review just email me at rtaylor@mariettaga.gov.\n\n\nSave Changes\nCancel\n\n\n\n", 
      "when": "30-08-2012"
    }
  ], 
  "answers_count": 1, 
  "author": "Lisa Slagle", 
  "id": 22117, 
  "score": "0", 
  "tags": [
    "Housing & Community Development", 
    "Finance and Budgeting", 
    "Contracts", 
    "Planning", 
    "Economic Development"
  ], 
  "text": "\n\nI am trying to gather sample RFPs for real estate services for the City of Fort Lauderdale.\nServices include appraisal, surplus propery sale, acquisitions, maintenance/Management and feasibility or market studies.\nDoes anyone have an RFP for all or some of these services that they could send me or direct where I can review?\n\n", 
  "title": "Real Estate Services for Municipalities", 
  "when": "30-08-2012"
}