{
  "answer_by": null, 
  "answers": [
    {
      "author": "Michael Embury", 
      "score": "0", 
      "text": "\n\nNorth Kingstown does charge for EMS runs.  A private firm bills insurance companies for a run; keeps 6% collected and the remainder of the funds are placed in a special fund to be used for purchasing fire equipment.\n\n\nNorth Kingstown does charge for EMS runs.  A private firm bills insurance companies for a run; keeps 6% collected and the remainder of the funds are placed in a special fund to be used for purchasing fire equipment.\n\n\nSave Changes\nCancel\n\n\n\n", 
      "when": "09-09-2014"
    }
  ], 
  "answers_count": 1, 
  "author": "Ashley Jacobs", 
  "id": 23278, 
  "score": "0", 
  "tags": [], 
  "text": "\n\nThese questions are for counties that provide fire service.  \n1.  Do you levy a tax for fire service, and if so, is it placed in a Special Revenue Fund?\n2.  Does your fire millage completely cover the cost of fire service, or is fire supplemented by the General Fund?\n3. Have you issued General Obligation bonds to purchase 800MHz radios?\n\n", 
  "title": "Funding Fire Service", 
  "when": "18-08-2014"
}