{
  "answer_by": null, 
  "answers": [
    {
      "author": "Alexandra Iannolo", 
      "score": "0", 
      "text": "\n\nHello,\nIn Milwaukee, the Milwaukee Economic Development Corporation Capital Access Program uses a loan loss reserve.\nhttp://city.milwaukee.gov/BusinessToolbox.htm#Tools1\nSeattle also passed an economic development plan that incorporated a loan loss reserve.\nhttp://clerk.ci.seattle.wa.us/~scripts/nph-brs.exe?s1=&s3=116961&s4=&s2=&s5=&Sect4=AND&l=20&Sect2=THESON&Sect3=PLURON&Sect5=CBORY&Sect6=HITOFF&d=ORDF&p=1&u=%2F~public%2Fcbory.htm&\nI also included a press release about the bill.\nhttp://www.seattle.gov/economicdevelopment/pdf_files/Energy%20Efficiency%20Grant%20OED%20Acceptance%20Release%20final%2010-4-10.pdf\nThe City of Yakima, WA passed a successful Economic Development Initiative in 2002 that involved a loan loss reserve.\nhttp://www.hud.gov/offices/cpd/economicdevelopment/programs/rc/tour/wa/yakima/gs1.cfm\nGulfport, MS also offers a Capital Access Loan Loss Reserve for businesses.\nhttp://www.gulfport-ms.gov/taxincentives.shtml\nBelow is a sample ordinance from Wichita, KS for a loan loss reserve program.\nhttp://www.wichita.gov/NR/rdonlyres/7F288F53-FB3F-40DA-A5B6-8C160455714A/0/Ordinance_No_45945.pdf\nYou can read more about the Michigan s Capital Access Program which includes loan loss reserves in this article from the W. E. Upjohn Institute for Employment Research.\nhttp://www.upjohn.org/publications/wp/95-33.pdf\nAli Iannolo\nKnowledge Network Intern\naiannolo@ICMA.org\n\n\nHello,\n\nIn Milwaukee, the Milwaukee Economic Development Corporation Capital Access Program uses a loan loss reserve.\nhttp://city.milwaukee.gov/BusinessToolbox.htm#Tools1\nSeattle also passed an economic development plan that incorporated a loan loss reserve.\nhttp://clerk.ci.seattle.wa.us/~scripts/nph-brs.exe?s1=&s3=116961&s4=&s2=&s5=&Sect4=AND&l=20&Sect2=THESON&Sect3=PLURON&Sect5=CBORY&Sect6=HITOFF&d=ORDF&p=1&u=%2F~public%2Fcbory.htm&\nI also included a press release about the bill.\nhttp://www.seattle.gov/economicdevelopment/pdf_files/Energy%20Efficiency%20Grant%20OED%20Acceptance%20Release%20final%2010-4-10.pdf\nThe City of Yakima, WA passed a successful Economic Development Initiative in 2002 that involved a loan loss reserve.\nhttp://www.hud.gov/offices/cpd/economicdevelopment/programs/rc/tour/wa/yakima/gs1.cfm\nGulfport, MS also offers a Capital Access Loan Loss Reserve for businesses.\nhttp://www.gulfport-ms.gov/taxincentives.shtml\nBelow is a sample ordinance from Wichita, KS for a loan loss reserve program.\nhttp://www.wichita.gov/NR/rdonlyres/7F288F53-FB3F-40DA-A5B6-8C160455714A/0/Ordinance_No_45945.pdf\nYou can read more about the Michigan s Capital Access Program which includes loan loss reserves in this article from the W. E. Upjohn Institute for Employment Research.\n http://www.upjohn.org/publications/wp/95-33.pdf\n\nAli Iannolo\nKnowledge Network Intern\naiannolo@ICMA.org\n\n\nSave Changes\nCancel\n\n\n\n", 
      "when": "11-11-2011"
    }
  ], 
  "answers_count": 1, 
  "author": "Toni Shope", 
  "id": 21491, 
  "score": "0", 
  "tags": [], 
  "text": "\n\nAn Alliance member is looking for examples of best practices in other communities for gap financing programs.\nThese would be economic development programs where City's provide a loan loss reserve to encourage private investment or actually loan funds to businesses.\nThank you for your help.\n\n", 
  "title": "Gap Financing Programs", 
  "when": "09-11-2011"
}