{
  "answer_by": null, 
  "answers": [
    {
      "author": "Shane Hale", 
      "score": "0", 
      "text": "\n\nKathryn:  I've brought in our local representative from ICMA-RC annually to meet individually with employees.  Normally, she'll do one or two presentations (that we select from her list), and will meet with anyone that is interested in 45 minute blocks.  My guess is that whoever your plan sponsor is, there is a similar service offered.\n\n\nKathryn:  I've brought in our local representative from ICMA-RC annually to meet individually with employees.  Normally, she'll do one or two presentations (that we select from her list), and will meet with anyone that is interested in 45 minute blocks.  My guess is that whoever your plan sponsor is, there is a similar service offered.\n\n\nSave Changes\nCancel\n\n\n\n", 
      "when": "28-07-2011"
    }
  ], 
  "answers_count": 1, 
  "author": "Kathryn Berkenpas", 
  "id": 21247, 
  "score": "0", 
  "tags": [
    "Economic Crisis", 
    "Career Resources"
  ], 
  "text": "\n\nAs public sector managers, what do you think is the most effective way to educate your employees about the importance of saving for retirement?\n\n", 
  "title": "Are your employees saving for retirement?", 
  "when": "28-07-2011"
}