{
  "answer_by": null, 
  "answers": [
    {
      "author": "Kevin Carter", 
      "score": "1", 
      "text": "\n\nHow bout The Municipal Meerkats? better than the Local Yokals.\n\n\nHow bout The Municipal Meerkats? better than the Local Yokals.\n\n\nSave Changes\nCancel\n\n\n\n", 
      "when": "10-03-2011"
    }, 
    {
      "author": "Jonathan Palmer", 
      "score": "0", 
      "text": "\n\nThe Bureaucrat's Bats\n\n\nThe Bureaucrat's Bats\n\n\nSave Changes\nCancel\n\n\n\n", 
      "when": "10-03-2011"
    }, 
    {
      "author": "Laura Hagg", 
      "score": "0", 
      "text": "\n\nCity Sliders?\n\n\nCity Sliders?\n\n\nSave Changes\nCancel\n\n\n\n", 
      "when": "10-03-2011"
    }
  ], 
  "answers_count": 3, 
  "author": "Municipal Meerkat", 
  "id": 20862, 
  "score": "1", 
  "tags": [
    "Healthy Living", 
    "Parks and Recreation"
  ], 
  "text": "\n\nGreetings! Softball season is almost upon us, and my colleagues and I at ICMA are looking forward to fielding a team this year. First things first though, we need a team name. As the captain of the team, I thought I would see if the Knowledge Network community would be willing to help us out by suggesting a new (perhaps local government themed) softball team name.\nI can't wait to see what you all come up with!\n\n", 
  "title": "ICMA Softball", 
  "when": "10-03-2011"
}