{
  "answer_by": null, 
  "answers": [
    {
      "author": "Pamela Muse", 
      "score": "0", 
      "text": "\n\nSteve, I hope the following is helpful:\nDesert Hot Springs\nhttp://www.cityofdhs.org/2012_Street_Rehabilitation_Project \nSanta Cruz, CA\nhttp://www.planning.org/consultants/viewrequest.htm?RequestID=11892\nPam\nPamela Muse\nWestern Regional Director\nAlliance for Innovation\n888-468-6450 Office\n480-231-3538 Text\npmuse@transformgov.org\nwww.transformgov.org\n\n\nSteve, I hope the following is helpful:\n\nDesert Hot Springs\nhttp://www.cityofdhs.org/2012_Street_Rehabilitation_Project \n\nSanta Cruz, CA\nhttp://www.planning.org/consultants/viewrequest.htm?RequestID=11892\n\nPam\n\nPamela Muse\nWestern Regional Director\nAlliance for Innovation\n888-468-6450 Office\n480-231-3538 Text\npmuse@transformgov.org\nwww.transformgov.org\n\n\nSave Changes\nCancel\n\n\n\n", 
      "when": "25-06-2013"
    }
  ], 
  "answers_count": 1, 
  "author": "Steve Chapman", 
  "id": 22613, 
  "score": "0", 
  "tags": [
    "Planning", 
    "Public Works"
  ], 
  "text": "\n\nI am looking for a Street Rehabilitation Master Plan RFQ document that I may modify for use in a project that I am currently developing for my jurisdiction. The finished master plan will include: Inventory and condition rating of streets; sidewalks; curb, gutter and inlets; identifying streets by use; development of standards; drainage plan; sidewalk and trail development and a street maintenance plan. Any RFQ documents close to this would be appreciated.\n\n", 
  "title": "Street Rehabilitation Master Plan RFQ document", 
  "when": "25-06-2013"
}