{
  "answer_by": null, 
  "answers": [], 
  "answers_count": 0, 
  "author": "Pamela Muse", 
  "id": 22166, 
  "score": "0", 
  "tags": [
    "Employee-Employer Relations"
  ], 
  "text": "\n\nWe are working on revising our City Shuttle Vehicle Policy for employees.  Please send copies of your policies ASAP. \nAlso, if you know of any state mandates that requires the city to provide employees transportation to work from public transit.\nThank you in advance.\nKarena McGee Shackelford\nCity of Fremont, CA \nKShackelford@fremont.gov  \nPam\nPamela Muse\nWestern Regional Director\n888-468-6450 Voice\n480-231-3538 Text\npmuse@transformgov.org\nwww.transformgov.org\n\n", 
  "title": "City Shuttle Policy for Employees", 
  "when": "19-09-2012"
}