{
  "answer_by": "14-02-2012", 
  "answers": [], 
  "answers_count": 0, 
  "author": "Anne Bell", 
  "id": 21668, 
  "score": "0", 
  "tags": [
    "Performance Management and Analytics"
  ], 
  "text": "\n\nOur agency would appreciate input on what other agencies use to track the information requested on the ICMA Information Technology Template.  Of interest is:\n1. Was tracking mechanism developed in-house (what software?) or was it purchased (cost?)?\n2. What process is used to collect the data (how often, by whom, how labor intensive)?\n3. Pros and cons of what you are using and how could it be improved?\n\n", 
  "title": "Performance Measurement Tracking Systems for Information Technology", 
  "when": "08-02-2012"
}