{
  "answer_by": null, 
  "answers": [
    {
      "author": "Alexandra Iannolo", 
      "score": "0", 
      "text": "\n\nHello,\nI found samples of Outstanding Citizen Award programs. The links below include information about each area's application and nomination process. You can contact these jurisdictions individually for more information. \nMuskegon, Michigan:\nttp://www.muskegon-mi.gov/outstanding-citizenship-award-application/\nColumbia, Missouri:\nhttp://www.columbiamochamber.com/pdf_files/Insert-2011%20Outstanding%20Citizen%20Award%20Applicationv2.pdf\nSomerset County, New Jersey:\nhttp://www.scbp.org/media/awards/outstanding-citizen-of-the-year-award\nSchaumburg, Illinois:\nhttp://www.ci.schaumburg.il.us/loc/Locate2/Pages/OutstandingCitizenAwardNomination.aspx\nBentonville, Arkansas:\nhttp://www.bentonvillear.com/docs/admin/outstanding_citizen_program.pdf\nAli Iannolo\nKnowledge Network Intern\naiannolo@ICMA.org\n\n\nHello,\n\nI found samples of Outstanding Citizen Award programs. The links below include information about each area's application and nomination process. You can contact these jurisdictions individually for more information. \n\nMuskegon, Michigan:\nttp://www.muskegon-mi.gov/outstanding-citizenship-award-application/\n\nColumbia, Missouri:\nhttp://www.columbiamochamber.com/pdf_files/Insert-2011%20Outstanding%20Citizen%20Award%20Applicationv2.pdf\n\nSomerset County, New Jersey:\nhttp://www.scbp.org/media/awards/outstanding-citizen-of-the-year-award\n\nSchaumburg, Illinois:\nhttp://www.ci.schaumburg.il.us/loc/Locate2/Pages/OutstandingCitizenAwardNomination.aspx\n\nBentonville, Arkansas:\nhttp://www.bentonvillear.com/docs/admin/outstanding_citizen_program.pdf\n\nAli Iannolo\nKnowledge Network Intern\naiannolo@ICMA.org\n\n\nSave Changes\nCancel\n\n\n\n", 
      "when": "12-08-2011"
    }
  ], 
  "answers_count": 1, 
  "author": "Nancy Deno", 
  "id": 21275, 
  "score": "0", 
  "tags": [], 
  "text": "\n\nHi\nDo you have any samples of successful Outstanding Citizen Award programs?  We will be creating the program and thought there may be some good ones out there showing the application and process.\nIf so, can I get a couple examples?\nthanks for your assistance.\nNancy\n\n", 
  "title": "Outstanding Citizen award program", 
  "when": "10-08-2011"
}